dexis/__init__.py
dexis-0.0.3.dist-info/LICENSE
dexis-0.0.3.dist-info/METADATA
dexis-0.0.3.dist-info/WHEEL
dexis-0.0.3.dist-info/top_level.txt
dexis-0.0.3.dist-info/RECORD
