Metadata-Version: 2.1
Name: dexis
Version: 0.0.3
Summary: Data Lexis
Home-page: https://github.com/i2mint/dexis
Author: OtoSense
License: apache-2.0
Platform: any
